douyin_video_mcp/__init__.py
douyin_video_mcp/__main__.py
douyin_video_mcp/config.py
douyin_video_mcp/douyin.py
douyin_video_mcp/server.py
douyin_video_mcp/asr/__init__.py
douyin_video_mcp/asr/base.py
douyin_video_mcp/asr/dashscope_provider.py
douyin_video_mcp/asr/factory.py
douyin_video_mcp/asr/fish_provider.py
douyin_video_mcp-1.0.1.dist-info/METADATA
douyin_video_mcp-1.0.1.dist-info/WHEEL
douyin_video_mcp-1.0.1.dist-info/entry_points.txt
douyin_video_mcp-1.0.1.dist-info/licenses/LICENSE
douyin_video_mcp-1.0.1.dist-info/RECORD
