Metadata-Version: 2.4
Name: douyin-video-mcp
Version: 1.0.1
Summary: MCP server for downloading Douyin videos and Using ASR API to extract text
Project-URL: Homepage, https://github.com/fancyboi999/douyin-video-mcp
Project-URL: Repository, https://github.com/fancyboi999/douyin-video-mcp
Project-URL: Issues, https://github.com/fancyboi999/douyin-video-mcp/issues
Author-email: fancyboi999 <fancyboi999@gmail.com>
License: MIT
License-File: LICENSE
Classifier: Development Status :: 3 - Alpha
Classifier: Intended Audience :: Developers
Classifier: License :: OSI Approved :: MIT License
Classifier: Programming Language :: Python :: 3
Classifier: Programming Language :: Python :: 3.10
Classifier: Programming Language :: Python :: 3.11
Classifier: Programming Language :: Python :: 3.12
Requires-Python: >=3.10
Requires-Dist: dashscope
Requires-Dist: ffmpeg-python
Requires-Dist: mcp>=1.0.0
Requires-Dist: requests
Requires-Dist: tqdm
